README.md
setup.py
notifiqueme/modulo.py
notifiqueme/test.py
notifiqueme.egg-info/PKG-INFO
notifiqueme.egg-info/SOURCES.txt
notifiqueme.egg-info/dependency_links.txt
notifiqueme.egg-info/requires.txt
notifiqueme.egg-info/top_level.txt