Metadata-Version: 2.1
Name: notifiqueme
Version: 1.0.0
Summary: Pacote para enviar mensagem no WhatsApp e SMS, de graça para desenvolvedores
Home-page: https://notifique-me.com
Author: Marcos Rafael Rodrigues
Author-email: rafaeljacuri@gmail.com
License: MIT License
Keywords: Pacote
Platform: UNKNOWN
